vectifyai/__init__.py
vectifyai/client.py
vectifyai-0.2.1.dist-info/METADATA
vectifyai-0.2.1.dist-info/WHEEL
vectifyai-0.2.1.dist-info/RECORD
