Metadata-Version: 2.1
Name: vectifyai
Version: 0.2.1
Summary: Python SDK for Vectify AI.
Author: Ray
Author-email: ray@vectify.ai
Requires-Python: >=3.8,<4.0
Classifier: Programming Language :: Python :: 3
Classifier: Programming Language :: Python :: 3.8
Classifier: Programming Language :: Python :: 3.9
Classifier: Programming Language :: Python :: 3.10
Classifier: Programming Language :: Python :: 3.11
Requires-Dist: requests (>=2.25.1,<3.0.0)
